oarepo_model_builder_drafts/__init__.py
oarepo_model_builder_drafts/builders/__init__.py
oarepo_model_builder_drafts/builders/parent_jsonschema_builder.py
oarepo_model_builder_drafts/datatypes/__init__.py
oarepo_model_builder_drafts/datatypes/draft.py
oarepo_model_builder_drafts/datatypes/components/__init__.py
oarepo_model_builder_drafts/datatypes/components/draft.py
oarepo_model_builder_drafts/datatypes/components/draft_tests.py
oarepo_model_builder_drafts/datatypes/components/draft_model/__init__.py
oarepo_model_builder_drafts/datatypes/components/draft_model/defaults.py
oarepo_model_builder_drafts/datatypes/components/draft_model/draft_parent.py
oarepo_model_builder_drafts/datatypes/components/draft_model/jsonschema.py
oarepo_model_builder_drafts/datatypes/components/draft_model/mapping.py
oarepo_model_builder_drafts/datatypes/components/draft_model/parent_marshmallow.py
oarepo_model_builder_drafts/datatypes/components/draft_model/parent_ui_marshmallow.py
oarepo_model_builder_drafts/datatypes/components/draft_model/pid.py
oarepo_model_builder_drafts/datatypes/components/draft_model/record.py
oarepo_model_builder_drafts/datatypes/components/draft_model/record_dumper.py
oarepo_model_builder_drafts/datatypes/components/draft_model/record_metadata.py
oarepo_model_builder_drafts/datatypes/components/draft_model/resource.py
oarepo_model_builder_drafts/datatypes/components/draft_model/search_options.py
oarepo_model_builder_drafts/datatypes/components/draft_model/service.py
oarepo_model_builder_drafts/events/__init__.py
oarepo_model_builder_drafts/events/after_model_loaded/__init__.py
oarepo_model_builder_drafts/events/after_model_loaded/version.py
oarepo_model_builder_drafts/invenio/__init__.py
oarepo_model_builder_drafts/invenio/invenio_drafts_config.py
oarepo_model_builder_drafts/invenio/invenio_drafts_has_draft_checkfield.py
oarepo_model_builder_drafts/invenio/invenio_drafts_parent_additional_fields.py
oarepo_model_builder_drafts-4.0.52.dist-info/METADATA
oarepo_model_builder_drafts-4.0.52.dist-info/WHEEL
oarepo_model_builder_drafts-4.0.52.dist-info/entry_points.txt
oarepo_model_builder_drafts-4.0.52.dist-info/top_level.txt
oarepo_model_builder_drafts-4.0.52.dist-info/RECORD
