Metadata-Version: 2.4
Name: oarepo-model-builder-drafts
Version: 4.0.52
Requires-Dist: oarepo-model-builder-tests>=3.1.0
Requires-Dist: oarepo-model-builder>=4.0.0
